pygml/__init__.py
pygml/axisorder.py
pygml/basics.py
pygml/dimensionality.py
pygml/georss.py
pygml/parse.py
pygml/pre_v32.py
pygml/types.py
pygml/v32.py
pygml/v33.py
pygml/v3_common.py
pygml-0.3.2.dist-info/licenses/LICENSE
tests/__init__.py
tests/test_axisorder.py
tests/test_basics.py
tests/test_dimensionality.py
tests/test_georss.py
tests/test_pre_v32.py
tests/test_v32.py
tests/test_v33.py
tests/util.py
pygml-0.3.2.dist-info/METADATA
pygml-0.3.2.dist-info/WHEEL
pygml-0.3.2.dist-info/top_level.txt
pygml-0.3.2.dist-info/RECORD
